{"pl_hostname\u2020": "Host Star Name", "pl_letter\u2020": "Planet Letter", "pl_name\u2020": "Planet Name", "pl_discmethod\u2020": "Discovery Method", "pl_controvflag\u2020": "Controversial Flag", "pl_pnum\u2020": "Number of Planets in System", "pl_orbper\u2020": "Orbital Period (days)", "pl_orbsmax\u2020": "Orbit Semi-Major Axis (au)", "pl_orbeccen\u2020": "Eccentricity", "pl_orbincl\u2020": "Inclination (deg)", "pl_bmassj\u2020": "Planet Mass or M*sin(i) [Jupiter mass]", "pl_bmassprov\u2020": "Planet Mass or M*sin(i) Provenance", "pl_radj\u2020": "Planet Radius (Jupiter radii)", "pl_dens\u2020": "Planet Density (g/cm**3)", "pl_ttvflag\u2020": "TTV Flag", "pl_kepflag\u2020": "Kepler Field Flag", "pl_k2flag\u2020": "K2 Mission Flag", "pl_nnotes\u2020": "Number of Notes", "ra_str\u2020": "RA (sexagesimal)", "dec_str\u2020": "Dec (sexagesimal) ", "ra\u2020": "RA (decimal degrees)", "dec\u2020": "Dec (decimal degrees)", "st_dist\u2020": "Distance (pc)", "gaia_dist\u2020": "Gaia Distance [pc]", "st_optmag\u2020": "Optical Magnitude [mag]", "st_optband\u2020": "Optical Magnitude Band", "gaia_gmag\u2020": "G-band (Gaia) [mag]", "st_teff\u2020": "Effective  Temperature (K)", "st_mass\u2020": "Stellar Mass (solar mass)", "st_rad\u2020": "Stellar Radius (solar radii)", "rowupdate\u2020": "Date of Last Update", "pl_facility\u2020": "Discovery Facility"}